counterfit_shims_seeed_python_dht.py
counterfit_shims_seeed_python_dht-0.1.0.dev1.dist-info/METADATA
counterfit_shims_seeed_python_dht-0.1.0.dev1.dist-info/WHEEL
counterfit_shims_seeed_python_dht-0.1.0.dev1.dist-info/top_level.txt
counterfit_shims_seeed_python_dht-0.1.0.dev1.dist-info/RECORD
