Metadata-Version: 2.1
Name: counterfit-shims-seeed-python-dht
Version: 0.1.0.dev1
Summary: Shims for the Seeed Grove DBT for the CounterFit virtual IoT device app
Home-page: https://github.com/CounterFit-IoT/CounterFit
Author: Jim Bennett
License: MIT
Keywords: iot grove seeed virtual hardware
Platform: UNKNOWN
Classifier: Development Status :: 2 - Pre-Alpha
Classifier: Intended Audience :: Developers
Classifier: Topic :: Software Development :: Libraries
Classifier: Topic :: System :: Hardware
Classifier: License :: OSI Approved :: MIT License
Classifier: Programming Language :: Python :: 3
Classifier: Programming Language :: Python :: 3.4
Classifier: Programming Language :: Python :: 3.5
Classifier: Programming Language :: Python :: 3.6
Classifier: Programming Language :: Python :: 3.7
Classifier: Programming Language :: Python :: 3.8
Classifier: Programming Language :: Python :: 3.9
Requires-Dist: requests
Requires-Dist: counterfit-connection
